splatlogger/__init__.py
splatlogger/__main__.py
splatlogger/data.py
splatlogger/match_logger.py
splatlogger/tcpgecko.py
splatlogger/tcpgecko_aroma.py
splatlogger-1.5.dist-info/licenses/LICENSE
splatlogger-1.5.dist-info/METADATA
splatlogger-1.5.dist-info/WHEEL
splatlogger-1.5.dist-info/entry_points.txt
splatlogger-1.5.dist-info/top_level.txt
splatlogger-1.5.dist-info/RECORD
