Metadata-Version: 2.4
Name: Splatlogger
Version: 1.5
Summary: A PID/PNID grabber and match logger for Splatoon using TCPGecko.
Author-email: Shadow Doggo <shadowdoggo@protonmail.com>
License-Expression: MIT
Project-URL: Source Code, https://github.com/spoongaming61/Splatlogger
Classifier: Programming Language :: Python :: 3
Classifier: Operating System :: OS Independent
Requires-Python: >=3.11
License-File: LICENSE
Requires-Dist: userpaths
Requires-Dist: requests
Dynamic: license-file
